[
    {
      "id": 0,
      "imageUrl": "https://sanayigazetesi.com.tr/wp-content/uploads/2022/12/mbbo-coach-usa-coach-premium-teaser-1536x864.jpg"
    },
    {
      "id": 1,
      "imageUrl": "https://static.bilet.com/images/bus/firmalar/kamil-koc.jpg"
    },
    {
      "id": 2,
      "imageUrl": "https://trthaberstatic.cdn.wp.trt.com.tr/resimler/1558000/otobus-1559935_1.jpg"
    },
    {
      "id": 3,
      "imageUrl": "https://trthaberstatic.cdn.wp.trt.com.tr/resimler/1558000/otobus-1559935_1.jpg"
    },
    {
      "id": 4,
      "imageUrl": "https://www.rudaw.net/s3/rudaw.net/ContentFiles/711211Image1.jpg?version=4978872"
    }
  ]